<?xml version="1.0" encoding="UTF-8"?>
<compilationUnit><packageDeclaration><name><simpleName><identifier>abc</identifier></simpleName></name></packageDeclaration><importDeclaration onDemand="false" static="false"><name><qualifiedName><name><qualifiedName><name><simpleName><identifier>a</identifier></simpleName></name><simpleName><identifier>b</identifier></simpleName></qualifiedName></name><simpleName><identifier>c</identifier></simpleName></qualifiedName></name></importDeclaration><importDeclaration onDemand="true" static="false"><name><qualifiedName><name><simpleName><identifier>x</identifier></simpleName></name><simpleName><identifier>y</identifier></simpleName></qualifiedName></name></importDeclaration><typeDeclaration interface="false"><simpleName><identifier>Test2</identifier></simpleName><extendsType><tp><simpleType><name><simpleName><identifier>Test</identifier></simpleName></name></simpleType></tp></extendsType><implementsType><tp><simpleType><name><simpleName><identifier>A</identifier></simpleName></name></simpleType></tp></implementsType></typeDeclaration><typeDeclaration interface="true"><simpleName><identifier>A</identifier></simpleName><extendsType><tp><simpleType><name><simpleName><identifier>B</identifier></simpleName></name></simpleType></tp></extendsType><extendsType><tp><simpleType><name><simpleName><identifier>C</identifier></simpleName></name></simpleType></tp></extendsType><extendsType><tp><simpleType><name><simpleName><identifier>D</identifier></simpleName></name></simpleType></tp></extendsType></typeDeclaration><typeDeclaration interface="false"><modifier>public</modifier><simpleName><identifier>Test</identifier></simpleName><bodyDeclaration id="" kind="fieldDeclaration"><fieldDeclaration><modifier>public</modifier><modifier>final</modifier><tp><primitiveType>int</primitiveType></tp><variableDeclarationFragment extrDimensions="0"><simpleName><identifier>x</identifier></simpleName><expression><numberLiteral>0</numberLiteral></expression></variableDeclarationFragment></fieldDeclaration></bodyDeclaration><bodyDeclaration id="" kind="fieldDeclaration"><fieldDeclaration><modifier>private</modifier><modifier>static</modifier><tp><simpleType><name><simpleName><identifier>XXX</identifier></simpleName></name></simpleType></tp><variableDeclarationFragment extrDimensions="0"><simpleName><identifier>b</identifier></simpleName><expression><nullLiteral/></expression></variableDeclarationFragment></fieldDeclaration></bodyDeclaration><bodyDeclaration id="" kind="initializer"><initializer><modifier>static</modifier><block><statement><variableDeclarationStatement><tp><primitiveType>int</primitiveType></tp><variableDeclarationFragment extrDimensions="0"><simpleName><identifier>a</identifier></simpleName><expression/></variableDeclarationFragment></variableDeclarationStatement></statement><statement><expressionStatement><expression><assignment><leftHandSide><expression><identifier>x</identifier></expression></leftHandSide><rightHandSide><expression><infixExpression hasExtendedOperands="false"><leftOperand><expression><identifier>x</identifier></expression></leftOperand><rightOperand><expression><numberLiteral>1</numberLiteral></expression></rightOperand><infixOperator>+</infixOperator></infixExpression></expression></rightHandSide><assignmentOperator>=</assignmentOperator></assignment></expression></expressionStatement></statement><statement><expressionStatement><expression><assignment><leftHandSide><expression><identifier>x</identifier></expression></leftHandSide><rightHandSide><expression><booleanLiteral>false</booleanLiteral></expression></rightHandSide><assignmentOperator>=</assignmentOperator></assignment></expression></expressionStatement></statement><statement><expressionStatement><expression><methodInvocation><expression><name><simpleName><identifier>System</identifier></simpleName></name><simpleName><identifier>out</identifier></simpleName></expression><simpleName><identifier>println</identifier></simpleName><argument><expression><stringLiteral>"bla"</stringLiteral></expression></argument></methodInvocation></expression></expressionStatement></statement><statement><expressionStatement><expression><assignment><leftHandSide><expression><identifier>sum</identifier></expression></leftHandSide><rightHandSide><expression><methodInvocation><expression><methodInvocation><expression><methodInvocation><expression><methodInvocation><expression><methodInvocation><expression><identifier>l</identifier></expression><simpleName><identifier>stream</identifier></simpleName></methodInvocation></expression><simpleName><identifier>map</identifier></simpleName><argument><expression/></argument></methodInvocation></expression><simpleName><identifier>filter</identifier></simpleName><argument><expression/></argument></methodInvocation></expression><simpleName><identifier>distinct</identifier></simpleName></methodInvocation></expression><simpleName><identifier>reduce</identifier></simpleName><argument><expression><numberLiteral>0</numberLiteral></expression></argument><argument><expression/></argument></methodInvocation></expression></rightHandSide><assignmentOperator>=</assignmentOperator></assignment></expression></expressionStatement></statement><statement><expressionStatement><expression><methodInvocation><expression><name><simpleName><identifier>System</identifier></simpleName></name><simpleName><identifier>out</identifier></simpleName></expression><simpleName><identifier>println</identifier></simpleName><argument><expression><stringLiteral>"bla"</stringLiteral></expression></argument></methodInvocation></expression></expressionStatement></statement></block></initializer></bodyDeclaration><bodyDeclaration id="" kind="methodDeclaration"><methodDeclaration constructor="false" extraDimensions="0"><modifier>public</modifier><simpleName><identifier>A</identifier></simpleName><returnType><tp><primitiveType>void</primitiveType></tp></returnType><formalParameter><singleVariableDeclaration extrDimentions="0"><tp><primitiveType>int</primitiveType></tp><simpleName><identifier>a</identifier></simpleName><expression/></singleVariableDeclaration></formalParameter><formalParameter><singleVariableDeclaration extrDimentions="0"><tp><primitiveType>int</primitiveType></tp><simpleName><identifier>b</identifier></simpleName><expression/></singleVariableDeclaration></formalParameter><thrownException><tp><name><simpleName><identifier>NullPointerException</identifier></simpleName></name></tp></thrownException><block/></methodDeclaration></bodyDeclaration><bodyDeclaration id="" kind="methodDeclaration"><methodDeclaration constructor="false" extraDimensions="0"><modifier>public</modifier><simpleName><identifier>B</identifier></simpleName><returnType><tp><primitiveType>void</primitiveType></tp></returnType><block/></methodDeclaration></bodyDeclaration><bodyDeclaration id="" kind="methodDeclaration"><methodDeclaration constructor="false" extraDimensions="0"><modifier>public</modifier><simpleName><identifier>distinctPrimarySum</identifier></simpleName><returnType><tp><primitiveType>void</primitiveType></tp></returnType><formalParameter><singleVariableDeclaration extrDimentions="0"><tp><simpleType><name><simpleName><identifier>String</identifier></simpleName></name></simpleType></tp><simpleName><identifier>numbers</identifier></simpleName><expression/></singleVariableDeclaration></formalParameter><block><statement><variableDeclarationStatement><tp><parameterizedType><tp><simpleType><name><simpleName><identifier>List</identifier></simpleName></name></simpleType></tp><typeArgument><tp><name><simpleName><identifier>String</identifier></simpleName></name></tp></typeArgument></parameterizedType></tp><variableDeclarationFragment extrDimensions="0"><simpleName><identifier>l</identifier></simpleName><expression><methodInvocation><expression><identifier>Arrays</identifier></expression><simpleName><identifier>asList</identifier></simpleName><argument><expression><identifier>numbers</identifier></expression></argument></methodInvocation></expression></variableDeclarationFragment></variableDeclarationStatement></statement><statement><variableDeclarationStatement><tp><primitiveType>int</primitiveType></tp><variableDeclarationFragment extrDimensions="0"><simpleName><identifier>sum</identifier></simpleName><expression><numberLiteral>0</numberLiteral></expression></variableDeclarationFragment></variableDeclarationStatement></statement><statement><expressionStatement><expression><assignment><leftHandSide><expression><identifier>sum</identifier></expression></leftHandSide><rightHandSide><expression><methodInvocation><expression><methodInvocation><expression><methodInvocation><expression><methodInvocation><expression><methodInvocation><expression><identifier>l</identifier></expression><simpleName><identifier>stream</identifier></simpleName></methodInvocation></expression><simpleName><identifier>map</identifier></simpleName><argument><expression/></argument></methodInvocation></expression><simpleName><identifier>filter</identifier></simpleName><argument><expression/></argument></methodInvocation></expression><simpleName><identifier>distinct</identifier></simpleName></methodInvocation></expression><simpleName><identifier>reduce</identifier></simpleName><argument><expression><numberLiteral>0</numberLiteral></expression></argument><argument><expression/></argument></methodInvocation></expression></rightHandSide><assignmentOperator>=</assignmentOperator></assignment></expression></expressionStatement></statement><statement><expressionStatement><expression><methodInvocation><expression><name><simpleName><identifier>System</identifier></simpleName></name><simpleName><identifier>out</identifier></simpleName></expression><simpleName><identifier>println</identifier></simpleName><argument><expression><infixExpression hasExtendedOperands="false"><leftOperand><expression><stringLiteral>"distinctPrimarySum result is: "</stringLiteral></expression></leftOperand><rightOperand><expression><identifier>sum</identifier></expression></rightOperand><infixOperator>+</infixOperator></infixExpression></expression></argument></methodInvocation></expression></expressionStatement></statement></block></methodDeclaration></bodyDeclaration><bodyDeclaration id="" kind="methodDeclaration"><methodDeclaration constructor="false" extraDimensions="0"><modifier>public</modifier><simpleName><identifier>distinctPrimarySum</identifier></simpleName><returnType><tp><primitiveType>void</primitiveType></tp></returnType><formalParameter><singleVariableDeclaration extrDimentions="0"><tp><arrayType dimensions="1"><tp><simpleType><name><simpleName><identifier>String</identifier></simpleName></name></simpleType></tp></arrayType></tp><simpleName><identifier>numbers</identifier></simpleName><expression/></singleVariableDeclaration></formalParameter><block><statement><variableDeclarationStatement><tp><parameterizedType><tp><simpleType><name><simpleName><identifier>List</identifier></simpleName></name></simpleType></tp><typeArgument><tp><name><simpleName><identifier>String</identifier></simpleName></name></tp></typeArgument></parameterizedType></tp><variableDeclarationFragment extrDimensions="0"><simpleName><identifier>l</identifier></simpleName><expression><methodInvocation><expression><identifier>Arrays</identifier></expression><simpleName><identifier>asList</identifier></simpleName><argument><expression><identifier>numbers</identifier></expression></argument></methodInvocation></expression></variableDeclarationFragment></variableDeclarationStatement></statement><statement><variableDeclarationStatement><tp><primitiveType>int</primitiveType></tp><variableDeclarationFragment extrDimensions="0"><simpleName><identifier>sum</identifier></simpleName><expression><numberLiteral>0</numberLiteral></expression></variableDeclarationFragment></variableDeclarationStatement></statement><statement><enhancedForStatement><formalParameter><singleVariableDeclaration extrDimentions="0"><tp><simpleType><name><simpleName><identifier>String</identifier></simpleName></name></simpleType></tp><simpleName><identifier>e</identifier></simpleName><expression/></singleVariableDeclaration></formalParameter><expression><identifier>l</identifier></expression><statement><block/></statement></enhancedForStatement></statement></block></methodDeclaration></bodyDeclaration></typeDeclaration></compilationUnit>